kalapaocr/__init__.py
kalapaocr/config.py
kalapaocr/recognize.py
kalapaocr/text_recognitor.py
kalapaocr/utils.py
kalapaocr/tool/__init__.py
kalapaocr/tool/config.py
kalapaocr/tool/img_proc.py
kalapaocr/tool/model_downloads.py
kalapaocr/tool/postprocess.py
kalapaocr/tool/vocab.py
kalapaocr-0.0.6.dist-info/LICENSE.txt
kalapaocr-0.0.6.dist-info/METADATA
kalapaocr-0.0.6.dist-info/WHEEL
kalapaocr-0.0.6.dist-info/top_level.txt
kalapaocr-0.0.6.dist-info/RECORD
