Metadata-Version: 2.1
Name: kalapaocr
Version: 0.0.6
Summary: A boiler plate to make pip package for AI model
Classifier: Programming Language :: Python :: 3
Classifier: Operating System :: OS Independent
Requires-Python: >=3.8
License-File: LICENSE.txt
Requires-Dist: setuptools
Requires-Dist: fuzzywuzzy
Requires-Dist: onnxruntime
Requires-Dist: opencv-python
Requires-Dist: pandas
Requires-Dist: tqdm
Requires-Dist: Pillow
